future/__init__.py
future/__init__.pyi
future/builtins/__init__.pyi
future/builtins/iterators.pyi
future/builtins/misc.pyi
future/moves/__init__.pyi
future/moves/_dummy_thread.pyi
future/moves/_markupbase.pyi
future/moves/_thread.pyi
future/moves/builtins.pyi
future/moves/collections.pyi
future/moves/configparser.pyi
future/moves/copyreg.pyi
future/moves/itertools.pyi
future/moves/pickle.pyi
future/moves/queue.pyi
future/moves/reprlib.pyi
future/moves/socketserver.pyi
future/moves/subprocess.pyi
future/moves/sys.pyi
future/moves/winreg.pyi
future/moves/dbm/__init__.pyi
future/moves/dbm/dumb.pyi
future/moves/dbm/gnu.pyi
future/moves/dbm/ndbm.pyi
future/moves/html/__init__.pyi
future/moves/html/entities.pyi
future/moves/html/parser.pyi
future/moves/http/__init__.pyi
future/moves/http/client.pyi
future/moves/http/cookiejar.pyi
future/moves/http/cookies.pyi
future/moves/http/server.pyi
future/moves/test/__init__.pyi
future/moves/test/support.pyi
future/moves/tkinter/__init__.pyi
future/moves/tkinter/colorchooser.pyi
future/moves/tkinter/commondialog.pyi
future/moves/tkinter/constants.pyi
future/moves/tkinter/dialog.pyi
future/moves/tkinter/dnd.pyi
future/moves/tkinter/filedialog.pyi
future/moves/tkinter/font.pyi
future/moves/tkinter/messagebox.pyi
future/moves/tkinter/scrolledtext.pyi
future/moves/tkinter/simpledialog.pyi
future/moves/tkinter/tix.pyi
future/moves/tkinter/ttk.pyi
future/moves/urllib/__init__.pyi
future/moves/urllib/error.pyi
future/moves/urllib/parse.pyi
future/moves/urllib/request.pyi
future/moves/urllib/response.pyi
future/moves/urllib/robotparser.pyi
future/moves/xmlrpc/__init__.pyi
future/moves/xmlrpc/client.pyi
future/moves/xmlrpc/server.pyi
future/standard_library/__init__.pyi
future/types/__init__.pyi
future/utils/__init__.pyi
future_stubs-0.18.0.0.dist-info/DESCRIPTION.rst
future_stubs-0.18.0.0.dist-info/LICENSE.txt
future_stubs-0.18.0.0.dist-info/METADATA
future_stubs-0.18.0.0.dist-info/RECORD
future_stubs-0.18.0.0.dist-info/WHEEL
future_stubs-0.18.0.0.dist-info/metadata.json
future_stubs-0.18.0.0.dist-info/top_level.txt
past/__init__.py
past/__init__.pyi
past/builtins/__init__.pyi
past/translation/__init__.pyi
past/types/__init__.pyi
past/utils/__init__.pyi
